dttimeframe/__init__.py
dttimeframe/timeFrame.py
dttimeframe-3.6.5.dist-info/LICENSE
dttimeframe-3.6.5.dist-info/METADATA
dttimeframe-3.6.5.dist-info/WHEEL
dttimeframe-3.6.5.dist-info/top_level.txt
dttimeframe-3.6.5.dist-info/RECORD
