Metadata-Version: 2.1
Name: dttimeframe
Version: 3.6.5
Summary: dtTimeFrame is a module that pack time track functions and subprocess call functions into one single class.
Home-page: https://github.com/SotongDJ/dtTimeFrame
Author: David Soh
Author-email: ln@trth.nl
Classifier: Development Status :: 4 - Beta
Classifier: Programming Language :: Python
Classifier: Programming Language :: Python :: 3
Classifier: Programming Language :: Python :: 3.7
Classifier: Programming Language :: Python :: 3.8
Classifier: Programming Language :: Python :: 3.9
Classifier: Programming Language :: Python :: 3.10
Classifier: Programming Language :: Python :: 3.11
Classifier: Programming Language :: Python :: Implementation :: CPython
Classifier: Programming Language :: Python :: Implementation :: PyPy
Classifier: License :: OSI Approved :: GNU General Public License v3 (GPLv3)
Classifier: Operating System :: OS Independent
License-File: LICENSE
